MANIFEST.in
README.rst
development.txt
requirements.txt
setup.cfg
setup.py
docs/source/conf.py
docs/source/index.rst
docs/source/internals.rst
docs/source/introduction.rst
docs/source/serialization.rst
docs/source/tutorial.rst
repocket/__init__.py
repocket/_cache.py
repocket/attributes.py
repocket/cli.py
repocket/connections.py
repocket/errors.py
repocket/manager.py
repocket/model.py
repocket/registry.py
repocket/util.py
repocket/version.py
repocket.egg-info/PKG-INFO
repocket.egg-info/SOURCES.txt
repocket.egg-info/dependency_links.txt
repocket.egg-info/entry_points.txt
repocket.egg-info/not-zip-safe
repocket.egg-info/requires.txt
repocket.egg-info/top_level.txt