Metadata-Version: 1.0
Name: repocket
Version: 0.1.29
Summary: simple active record for redis
Home-page: http://repocket.readthedocs.org
Author: Gabriel Falcao
Author-email: gabriel@nacaolivre.org
License: UNKNOWN
Platform: UNKNOWN
